{
    "ATTRIBUTES": {
        "construction": "Knit",
        "length": "Short",
        "material": "Cotton blend",
        "occasion": "Casual",
        "swatchSize": "XS",
        "swatchcolor": "Pink"
    },
    "BRAND": "Albini",
    "CATEGORY": "Topwear",
    "CATENTRY_ID": "10250",
    "LONGDESCRIPTION": "Strapless knit summer dress perfect for picnics and life in the city. The polka dots and brown belt add style to simplicity.",
    "MODATTRIBUTES": "'Knit construction', 'Casual occasion', 'XS size', 'Pink color', 'Cotton blend material', 'Short length'",
    "NAME": "Albini Casual Knit Strapless Dress",
    "OFFERPRICE": 50.0,
    "PARENTPARTNUMBER": "AuroraWMDRS-15",
    "PARTNUMBER": "AuroraWMDRS-223",
    "SHORTDESCRIPTION": "Strapless knit A-line summer dress with polka dots"
}