{
    "ATTRIBUTES": {
        "construction": "Knit",
        "length": "Short",
        "material": "Cotton blend",
        "occasion": "Career, Casual",
        "swatchSize": "L",
        "swatchcolor": "Pink"
    },
    "BRAND": "Versatil",
    "CATEGORY": "Topwear",
    "CATENTRY_ID": "10592",
    "LONGDESCRIPTION": "A simple and elegant dress with a ruffled top and lace straps, along with an empire waist. The layered, gored skirt completes the look, and you'll feel as light as a cloud wearing this chic dress.",
    "NAME": "Versatil Casual Evening Dress",
    "OFFERPRICE": 50.0,
    "PARENTPARTNUMBER": "AuroraWMDRS-34",
    "PARTNUMBER": "AuroraWMDRS-578",
    "SHORTDESCRIPTION": "Sleeveless slip dress with ruffled front and lace work"
}