{
    "ATTRIBUTES": {
        "WomenPantsColor": "Black",
        "WomenPantsSize": "S"
    },
    "BRAND": "Versatil",
    "CATEGORY": "Bottomwear",
    "CATENTRY_ID": "11026",
    "LONGDESCRIPTION": "These black striped flared pants look great as part of a business suit. They present a stylish and modern look. The vertical stripes add to the height and will make you look taller.",
    "MODATTRIBUTES": "'S size', 'Black color'",
    "NAME": "Versatil Black Striped Pants",
    "OFFERPRICE": 80.0,
    "PARENTPARTNUMBER": "WCL004_0416",
    "PARTNUMBER": "WCL004_041602",
    "SHORTDESCRIPTION": "Black striped flared pants"
}